[{"created_at":"2022-12-24T21:06:38.000Z","title":"Merry Christmas, HN","url":"https://news.ycombinator.com/item?id=34121082","author":"Thorentis","points":1659,"num_comments":221,"objectID":"34121082"},{"created_at":"2022-12-31T15:43:54.000Z","title":"Draw SVG rope using JavaScript","url":"https://muffinman.io/blog/draw-svg-rope-using-javascript/","author":"stankot","points":1211,"num_comments":66,"objectID":"34197379"},{"created_at":"2022-12-28T15:21:29.000Z","title":"Hard truths I learned when I got laid off from my SWE job","url":"https://www.stevenbuccini.com/8-hard-truths-on-getting-laid-off","author":"sbuccini","points":1012,"num_comments":570,"objectID":"34161822"},{"created_at":"2022-12-28T21:07:09.000Z","title":"Barnes and Noble's surprising turnaround","url":"https://tedgioia.substack.com/p/what-can-we-learn-from-barnes-and","author":"AlbertCory","points":917,"num_comments":484,"objectID":"34165960"},{"created_at":"2022-12-29T23:17:43.000Z","title":"Golang disables Nagle's Algorithm by default","url":"https://withinboredom.info/blog/2022/12/29/golang-is-evil-on-shitty-networks/","author":"withinboredom","points":806,"num_comments":371,"objectID":"34179426"},{"created_at":"2022-12-26T16:27:11.000Z","title":"How to Befriend Crows","url":"https://fediscience.org/@ct_bergstrom/109571409346371116","author":"karmanyaahm","points":800,"num_comments":216,"objectID":"34139048"},{"created_at":"2022-12-29T19:05:23.000Z","title":"A search engine for searching books in the Z-Library index on the IPFS network","url":"https://zlib.zu1k.com/","author":"baptiste313","points":776,"num_comments":203,"objectID":"34176479"},{"created_at":"2022-12-29T19:13:18.000Z","title":"Pelé has died","url":"https://www.nytimes.com/2022/12/29/sports/soccer/pele-dead.html","author":"mfiguiere","points":735,"num_comments":240,"objectID":"34176601"},{"created_at":"2022-12-27T17:51:19.000Z","title":"US Government demands direct police access to European biometric data [pdf]","url":"https://digit.so36.net/Data/20221227_HIP_EBSP_IBIS.pdf","author":"diimdeep","points":651,"num_comments":402,"objectID":"34151382"},{"created_at":"2022-12-25T01:58:38.000Z","title":"“Nobody cares about your blog”","url":"https://mssprovenance.blogspot.com/2022/12/nobody-cares-about-your-blog.html","author":"barry-cotter","points":617,"num_comments":126,"objectID":"34123302"}]